{"id":"0bb07793f67f41848647e01558f9b34e","examples":[{"content":"Is Ethereum hit 10k $\n\n#ETH #Ethereum","seen_by":[{"annotator":"laurens.de.bruin99@gmail.com","annotator_id":1}],"metadata":{"":7,"id":"1511785711556435973","label":"?"},"example_id":"c600cd7a-7271-4f39-990e-8682947a8ccc","annotations":[],"classifications":[{"correct":null,"class_id":"2fa03333-2670-491d-942e-6fe416b1e212","reviewed":false,"classname":"Unrelated","example_id":"c600cd7a-7271-4f39-990e-8682947a8ccc","classified_by":[{"annotator":"laurens.de.bruin99@gmail.com","timestamp":"2022-04-16T13:14:24.794+00:00","annotator_id":1}],"definition_id":"0bb07793-f67f-4184-8647-e01558f9b34e"}]},{"content":"- \nBTC price: $40,110 / £30,792 \n\n24.93 Naks per USD\n32.48 Naks per GBP\n \n&lt;going UP!&gt; \n\nWhen 1 #Nak = 1 #Dollar we shall have a 1m dollar Bitcoin \nWhen 1 Nak = 1 GBPound then #Bitcoin = £1m etc. \n#Bitcoinprice \n\n11/04/2022  21:30:28 GMT https://t.co/TifT9WDioa","seen_by":[{"annotator":"laurens.de.bruin99@gmail.com","annotator_id":1}],"metadata":{"":0,"id":"1513615505512312832","label":"?"},"example_id":"c4fc575b-cded-4491-9c10-2062ca541d57","annotations":[],"classifications":[{"correct":null,"class_id":"57fba206-3865-4375-8c99-40602e7aa718","reviewed":false,"classname":"Neutral","example_id":"c4fc575b-cded-4491-9c10-2062ca541d57","classified_by":[{"annotator":"laurens.de.bruin99@gmail.com","timestamp":"2022-04-16T13:13:03.2+00:00","annotator_id":1}],"definition_id":"0bb07793-f67f-4184-8647-e01558f9b34e"}]},{"content":"@cardano_whale Things that will last. Bull or bear, actual utility.","seen_by":[{"annotator":"laurens.de.bruin99@gmail.com","annotator_id":1}],"metadata":{"":1,"id":"1506479266573307905","label":"?"},"example_id":"dda1a752-f124-4502-8cca-a5e3d66e0ce3","annotations":[],"classifications":[{"correct":null,"class_id":"2fa03333-2670-491d-942e-6fe416b1e212","reviewed":false,"classname":"Unrelated","example_id":"dda1a752-f124-4502-8cca-a5e3d66e0ce3","classified_by":[{"annotator":"laurens.de.bruin99@gmail.com","timestamp":"2022-04-16T13:12:17.168+00:00","annotator_id":1}],"definition_id":"0bb07793-f67f-4184-8647-e01558f9b34e"}]},{"content":"DXY is starting to look bearish.\n\nThe RSI is at an high level, getting ready for a correction.\n\nIt also happen that #BTC is at support now.\n\nWe will have inflation data release tomorrow. \n\nIs it time for a long and sustained pump? #Cryptos #bitcoin #blockchain #DXY https://t.co/UJUiS1S9qE","seen_by":[{"annotator":"laurens.de.bruin99@gmail.com","annotator_id":1}],"metadata":{"":2,"id":"1513620622345129990","label":"?"},"example_id":"7f01b815-f073-47c8-9a92-b1cf4d16bbd0","annotations":[],"classifications":[{"correct":null,"class_id":"6d58be54-780e-41ca-95e9-aedfc3f93432","reviewed":false,"classname":"Negative","example_id":"7f01b815-f073-47c8-9a92-b1cf4d16bbd0","classified_by":[{"annotator":"laurens.de.bruin99@gmail.com","timestamp":"2022-04-16T13:15:20.589+00:00","annotator_id":1}],"definition_id":"0bb07793-f67f-4184-8647-e01558f9b34e"}]},{"content":"With the current trend of btc, it will continue to rise this week. I believe it should rise back to $60,000 in the first half of this year.#bitcoin https://t.co/ZmUeszcCK4","seen_by":[{"annotator":"laurens.de.bruin99@gmail.com","annotator_id":1}],"metadata":{"":3,"id":"1513531702307880963","label":"?"},"example_id":"b5f63614-674d-461d-b9bb-2b1c9fc21aea","annotations":[],"classifications":[{"correct":null,"class_id":"7f749090-d1fe-4bbb-9fd7-75aae0b529cc","reviewed":false,"classname":"Positive","example_id":"b5f63614-674d-461d-b9bb-2b1c9fc21aea","classified_by":[{"annotator":"laurens.de.bruin99@gmail.com","timestamp":"2022-04-16T13:11:03+00:00","annotator_id":1}],"definition_id":"0bb07793-f67f-4184-8647-e01558f9b34e"}]},{"content":"#Binance Futures Liquidated On:\n\n🔵 $COTI Worth 221,471 USDT\n🔵 $NEO Worth 323,433 USDT\n🔵 $BTS Worth 472,806 USDT\n🔴 $GMT Worth 260,929 USDT\n\n#cryptocurrency #cryptotrading #AltCoins #BTC  54395267","seen_by":[{"annotator":"laurens.de.bruin99@gmail.com","annotator_id":1}],"metadata":{"":4,"id":"1511784332758769672","label":"?"},"example_id":"cbfcd3f2-01a4-4106-a1bf-d034fafbea24","annotations":[],"classifications":[{"correct":null,"class_id":"2fa03333-2670-491d-942e-6fe416b1e212","reviewed":false,"classname":"Unrelated","example_id":"cbfcd3f2-01a4-4106-a1bf-d034fafbea24","classified_by":[{"annotator":"laurens.de.bruin99@gmail.com","timestamp":"2022-04-16T13:12:12.797+00:00","annotator_id":1}],"definition_id":"0bb07793-f67f-4184-8647-e01558f9b34e"}]},{"content":"30 USD en #ElSalvador #BitcoinDay te dieren 63,900 sat. \nAhora 63,900 sat son 27.90 USD (-6.99%)\n\n1 BTC = 43,673.80 USD\n1 USD = 2,290 Sat\nel 06 Apr 2022 02:30 PM CDT\n\n1 BTC = 46,948.36 USD\n1 USD = 2,130 sat\nel Mar 07 Sep 2021 10:00 AM CST\n\n#Bitcoin","seen_by":[{"annotator":"laurens.de.bruin99@gmail.com","annotator_id":1}],"metadata":{"":5,"id":"1511788335362154498","label":"?"},"example_id":"31dee941-09af-439d-9f6b-288a4a0dce2e","annotations":[],"classifications":[{"correct":null,"class_id":"2fa03333-2670-491d-942e-6fe416b1e212","reviewed":false,"classname":"Unrelated","example_id":"31dee941-09af-439d-9f6b-288a4a0dce2e","classified_by":[{"annotator":"laurens.de.bruin99@gmail.com","timestamp":"2022-04-16T13:16:10.767+00:00","annotator_id":1}],"definition_id":"0bb07793-f67f-4184-8647-e01558f9b34e"}]},{"content":"↓ #BZRX PRICE = 0,117897\nRank = #439\n#AVAX = 809,86 $BZRX\n1D: +0.31%\nCHANGING = -32,52 ▅▃▁","seen_by":[{"annotator":"laurens.de.bruin99@gmail.com","annotator_id":1}],"metadata":{"":10,"id":"1511285816991039493","label":"?"},"example_id":"cfd8ef02-1738-4b44-b2bb-2436d148a794","annotations":[],"classifications":[{"correct":null,"class_id":"57fba206-3865-4375-8c99-40602e7aa718","reviewed":false,"classname":"Neutral","example_id":"cfd8ef02-1738-4b44-b2bb-2436d148a794","classified_by":[{"annotator":"laurens.de.bruin99@gmail.com","timestamp":"2022-04-16T13:15:01.395+00:00","annotator_id":1}],"definition_id":"0bb07793-f67f-4184-8647-e01558f9b34e"}]},{"content":"$DAG Buy setup (Gem Call) \n\n#1000xgem #DAG #constellationnetwork #BTC #TradingSignals https://t.co/VA7jue93NE","seen_by":[{"annotator":"laurens.de.bruin99@gmail.com","annotator_id":1}],"metadata":{"":43,"id":"1513524372161675272","label":"?"},"example_id":"b0a82d5f-1b63-4b46-b123-bc292c7cbd40","annotations":[],"classifications":[{"correct":null,"class_id":"2fa03333-2670-491d-942e-6fe416b1e212","reviewed":false,"classname":"Unrelated","example_id":"b0a82d5f-1b63-4b46-b123-bc292c7cbd40","classified_by":[{"annotator":"laurens.de.bruin99@gmail.com","timestamp":"2022-04-16T13:15:35.577+00:00","annotator_id":1}],"definition_id":"0bb07793-f67f-4184-8647-e01558f9b34e"}]},{"content":"#Binance Futures Liquidated On:\n\n🟢 $LRC Worth 508,987 USDT\n🔴 $YFI Worth 480,621 USDT\n🟢 $IOTX Worth 312,309 USDT\n🔵 $ZEN Worth 347,635 USDT\n\n#BTC   👇👇 learn &amp; join me\n\n🔸  https://t.co/S1kEg6W7zj\n\n 92263879 https://t.co/FTrTYy5voR","seen_by":[{"annotator":"laurens.de.bruin99@gmail.com","annotator_id":1}],"metadata":{"":6,"id":"1513663464228724738","label":"?"},"example_id":"50a29dc1-5c74-41eb-87f7-4732e1431e00","annotations":[],"classifications":[{"correct":null,"class_id":"2fa03333-2670-491d-942e-6fe416b1e212","reviewed":false,"classname":"Unrelated","example_id":"50a29dc1-5c74-41eb-87f7-4732e1431e00","classified_by":[{"annotator":"laurens.de.bruin99@gmail.com","timestamp":"2022-04-16T13:13:09.549+00:00","annotator_id":1}],"definition_id":"0bb07793-f67f-4184-8647-e01558f9b34e"}]},{"content":"Pairs:MANAUSDT \n SELL:2.63190\n Time :4/2/2022 11:52:47 PM\n Average Decision:48.97134 FourHour \n Estimated Direction: DOWN\n #BTC #BNTETH #Bitcoin #RSİ #Bollinger -It is not investment advice. You can visit our profile for your own alarms. YTD. 9:15:38 PM","seen_by":[{"annotator":"laurens.de.bruin99@gmail.com","annotator_id":1}],"metadata":{"":8,"id":"1510320200306024450","label":"?"},"example_id":"827a1201-8951-44a1-89a8-65db00f91d31","annotations":[],"classifications":[{"correct":null,"class_id":"6d58be54-780e-41ca-95e9-aedfc3f93432","reviewed":false,"classname":"Negative","example_id":"827a1201-8951-44a1-89a8-65db00f91d31","classified_by":[{"annotator":"laurens.de.bruin99@gmail.com","timestamp":"2022-04-16T13:17:39.145+00:00","annotator_id":1}],"definition_id":"0bb07793-f67f-4184-8647-e01558f9b34e"}]},{"content":"Cryptocurrency Market | Coin Prices [15m]🔔 #Bitcoin Price: $43443.86🔔 #Ethereum Price: $3225.52🔔 #Bnb Price: $43… https://t.co/x5YMlvMroC","seen_by":[{"annotator":"laurens.de.bruin99@gmail.com","annotator_id":1}],"metadata":{"":9,"id":"1513672038837362700","label":"?"},"example_id":"6080a56b-4e69-42b3-92cb-d5290cba471f","annotations":[],"classifications":[{"correct":null,"class_id":"57fba206-3865-4375-8c99-40602e7aa718","reviewed":false,"classname":"Neutral","example_id":"6080a56b-4e69-42b3-92cb-d5290cba471f","classified_by":[{"annotator":"laurens.de.bruin99@gmail.com","timestamp":"2022-04-16T13:12:45.506+00:00","annotator_id":1}],"definition_id":"0bb07793-f67f-4184-8647-e01558f9b34e"}]},{"content":"#BTC  Holding support ✅🧘‍♂️ https://t.co/DeIXwTZ4Y8","seen_by":[{"annotator":"laurens.de.bruin99@gmail.com","annotator_id":1}],"metadata":{"":11,"id":"1513696498378317829","label":"?"},"example_id":"417becd7-1e65-4f38-a162-cdb0ccaa399c","annotations":[],"classifications":[{"correct":null,"class_id":"7f749090-d1fe-4bbb-9fd7-75aae0b529cc","reviewed":false,"classname":"Positive","example_id":"417becd7-1e65-4f38-a162-cdb0ccaa399c","classified_by":[{"annotator":"laurens.de.bruin99@gmail.com","timestamp":"2022-04-16T13:12:27.574+00:00","annotator_id":1}],"definition_id":"0bb07793-f67f-4184-8647-e01558f9b34e"}]},{"content":"A recent whale alert misassociated an F2pool cold wallet with #Bitcoin #(BTC) exchange Mt. Gox, which transferred 6,800 BTC to an unknown wallet just days after the former CEO Mark Karpeles revealed plans to redistribute BTC worth $6 billion to its creditors.","seen_by":[{"annotator":"laurens.de.bruin99@gmail.com","annotator_id":1}],"metadata":{"":12,"id":"1510630758553374722","label":"?"},"example_id":"e4388637-aca1-4343-86ce-5bf313a68abf","annotations":[],"classifications":[{"correct":null,"class_id":"2fa03333-2670-491d-942e-6fe416b1e212","reviewed":false,"classname":"Unrelated","example_id":"e4388637-aca1-4343-86ce-5bf313a68abf","classified_by":[{"annotator":"laurens.de.bruin99@gmail.com","timestamp":"2022-04-16T13:13:23.627+00:00","annotator_id":1}],"definition_id":"0bb07793-f67f-4184-8647-e01558f9b34e"}]},{"content":"#BTC history 👇👇\n\n2013 - $88.06\n2014 - $627.46\n2015 - $290.67\n2016 - $658.15\n2017 - $2,364.32\n2018 - $6,230.59\n2019 - $11,804.56\n2020 - $9,297.48\n2021 - $32,845.64\nNow - $40,204.71 📉\n\nWhere will $BTC be at next year?","seen_by":[{"annotator":"laurens.de.bruin99@gmail.com","annotator_id":1}],"metadata":{"":13,"id":"1513598722713825285","label":"?"},"example_id":"a4adca17-714f-4a47-b33a-38bde2f750dc","annotations":[],"classifications":[{"correct":null,"class_id":"57fba206-3865-4375-8c99-40602e7aa718","reviewed":false,"classname":"Neutral","example_id":"a4adca17-714f-4a47-b33a-38bde2f750dc","classified_by":[{"annotator":"laurens.de.bruin99@gmail.com","timestamp":"2022-04-16T13:13:45.952+00:00","annotator_id":1}],"definition_id":"0bb07793-f67f-4184-8647-e01558f9b34e"}]},{"content":"Where do you think the market is directed to next?\n\n#Trading #crypto #hodl #Bitcoin","seen_by":[{"annotator":"laurens.de.bruin99@gmail.com","annotator_id":1}],"metadata":{"":14,"id":"1510643554602921991","label":"?"},"example_id":"6537d885-df4a-4964-8725-061fbcb403af","annotations":[],"classifications":[{"correct":null,"class_id":"2fa03333-2670-491d-942e-6fe416b1e212","reviewed":false,"classname":"Unrelated","example_id":"6537d885-df4a-4964-8725-061fbcb403af","classified_by":[{"annotator":"laurens.de.bruin99@gmail.com","timestamp":"2022-04-16T13:15:31.795+00:00","annotator_id":1}],"definition_id":"0bb07793-f67f-4184-8647-e01558f9b34e"}]},{"content":"#SNX - long alert 💸🤑\n\nExchange     : BINANCE\nMarket         : $SNX - $USDT\nVolume        : $170,038\nPrice            : $4.5636\n\n$BTC #BTC $ETH #ETH\n\nFor live Whale Trade Flow, check - https://t.co/qEq8Ymgdoc https://t.co/m8AGGRFmff","seen_by":[{"annotator":"laurens.de.bruin99@gmail.com","annotator_id":1}],"metadata":{"":15,"id":"1513680004961300481","label":"?"},"example_id":"4d328dce-656e-4cc6-a710-1f543e504433","annotations":[],"classifications":[{"correct":null,"class_id":"7f749090-d1fe-4bbb-9fd7-75aae0b529cc","reviewed":false,"classname":"Positive","example_id":"4d328dce-656e-4cc6-a710-1f543e504433","classified_by":[{"annotator":"laurens.de.bruin99@gmail.com","timestamp":"2022-04-16T13:17:31.135+00:00","annotator_id":1}],"definition_id":"0bb07793-f67f-4184-8647-e01558f9b34e"}]},{"content":"@EMDARKS1 #Bitcoin  has AGAIN dipped deeper into the old resistance area of $41k in an effort to flip it into a new support area before next week #Hold #Buy\n\n@Mt_49k is a super underrated Bitcoiner\nI've been taking her tweets and tips seriously &amp; I've been doing superb. \n\nFollow her","seen_by":[{"annotator":"laurens.de.bruin99@gmail.com","annotator_id":1}],"metadata":{"":16,"id":"1513525016565989381","label":"?"},"example_id":"93c05863-0864-43a2-892e-eaf090e6b321","annotations":[],"classifications":[{"correct":null,"class_id":"6d58be54-780e-41ca-95e9-aedfc3f93432","reviewed":false,"classname":"Negative","example_id":"93c05863-0864-43a2-892e-eaf090e6b321","classified_by":[{"annotator":"laurens.de.bruin99@gmail.com","timestamp":"2022-04-16T13:14:37.207+00:00","annotator_id":1}],"definition_id":"0bb07793-f67f-4184-8647-e01558f9b34e"}]},{"content":"@Hotmoontoken @XTexchange Let's waste no time... @Hotmoontoken is gonna be launching real soon... #HotMoonArmy #crypto #investing","seen_by":[{"annotator":"laurens.de.bruin99@gmail.com","annotator_id":1}],"metadata":{"":17,"id":"1510649463056044050","label":"?"},"example_id":"b0db4ec8-2aa1-4238-a5ad-2a19866ee582","annotations":[],"classifications":[{"correct":null,"class_id":"2fa03333-2670-491d-942e-6fe416b1e212","reviewed":false,"classname":"Unrelated","example_id":"b0db4ec8-2aa1-4238-a5ad-2a19866ee582","classified_by":[{"annotator":"laurens.de.bruin99@gmail.com","timestamp":"2022-04-16T13:17:46.906+00:00","annotator_id":1}],"definition_id":"0bb07793-f67f-4184-8647-e01558f9b34e"}]},{"content":"In summer, I want it to protect from the sun.🤣#BTC #ETH #coinbase https://t.co/ZA0GbVeHDL","seen_by":[{"annotator":"laurens.de.bruin99@gmail.com","annotator_id":1}],"metadata":{"":18,"id":"1513678501580513281","label":"?"},"example_id":"b1c2f0d9-db41-45fe-995d-feda3d5b4402","annotations":[],"classifications":[{"correct":null,"class_id":"2fa03333-2670-491d-942e-6fe416b1e212","reviewed":false,"classname":"Unrelated","example_id":"b1c2f0d9-db41-45fe-995d-feda3d5b4402","classified_by":[{"annotator":"laurens.de.bruin99@gmail.com","timestamp":"2022-04-16T13:13:05.953+00:00","annotator_id":1}],"definition_id":"0bb07793-f67f-4184-8647-e01558f9b34e"}]},{"content":"@RMoonOfficial @CoinMarketCap Let's do it\n\n #TRX #LINK #CryptoNews","seen_by":[{"annotator":"laurens.de.bruin99@gmail.com","annotator_id":1}],"metadata":{"":19,"id":"1510329782520721412","label":"?"},"example_id":"2b480c88-8665-4137-a5cb-13ec5a285b5e","annotations":[],"classifications":[{"correct":null,"class_id":"2fa03333-2670-491d-942e-6fe416b1e212","reviewed":false,"classname":"Unrelated","example_id":"2b480c88-8665-4137-a5cb-13ec5a285b5e","classified_by":[{"annotator":"laurens.de.bruin99@gmail.com","timestamp":"2022-04-16T13:14:28.046+00:00","annotator_id":1}],"definition_id":"0bb07793-f67f-4184-8647-e01558f9b34e"}]},{"content":"When @PrimrozeTV learns that Minecraft Steve is in Super Smash Bros😳 #Bitcoin2022 #Bitcoin https://t.co/0B9D1bIJEY","seen_by":[{"annotator":"laurens.de.bruin99@gmail.com","annotator_id":1}],"metadata":{"":20,"id":"1512111467797127176","label":"?"},"example_id":"b78766e4-fa33-4985-9e87-4d183567715c","annotations":[],"classifications":[{"correct":null,"class_id":"2fa03333-2670-491d-942e-6fe416b1e212","reviewed":false,"classname":"Unrelated","example_id":"b78766e4-fa33-4985-9e87-4d183567715c","classified_by":[{"annotator":"laurens.de.bruin99@gmail.com","timestamp":"2022-04-16T13:12:35.113+00:00","annotator_id":1}],"definition_id":"0bb07793-f67f-4184-8647-e01558f9b34e"}]},{"content":"@trylolli 3.5% #bitcoin back at Sephora and boosted with @fold_app \n\nTotal 5% back - pretty good! https://t.co/FQVnpPWAZ3","seen_by":[{"annotator":"laurens.de.bruin99@gmail.com","annotator_id":1}],"metadata":{"":21,"id":"1512111769178808324","label":"?"},"example_id":"366f10c7-bf1a-40ff-808d-4ff2cabaf68a","annotations":[],"classifications":[{"correct":null,"class_id":"2fa03333-2670-491d-942e-6fe416b1e212","reviewed":false,"classname":"Unrelated","example_id":"366f10c7-bf1a-40ff-808d-4ff2cabaf68a","classified_by":[{"annotator":"laurens.de.bruin99@gmail.com","timestamp":"2022-04-16T13:14:09.183+00:00","annotator_id":1}],"definition_id":"0bb07793-f67f-4184-8647-e01558f9b34e"}]},{"content":"It is official! My EpochSec LLC application was approved! Also have my https://t.co/WSM7frUwVH (and .com) domain. Even have my @adahandle's $epochsec and $epochsec.io for completion ... try them out😉\n#Cardano $ADA #CardanoCommunity https://t.co/zMqC1Vb7u5","seen_by":[{"annotator":"laurens.de.bruin99@gmail.com","annotator_id":1}],"metadata":{"":22,"id":"1513686646981636099","label":"?"},"example_id":"89f6c759-0c67-43f9-9192-7fc9918f6d86","annotations":[],"classifications":[{"correct":null,"class_id":"2fa03333-2670-491d-942e-6fe416b1e212","reviewed":false,"classname":"Unrelated","example_id":"89f6c759-0c67-43f9-9192-7fc9918f6d86","classified_by":[{"annotator":"laurens.de.bruin99@gmail.com","timestamp":"2022-04-16T13:14:18.389+00:00","annotator_id":1}],"definition_id":"0bb07793-f67f-4184-8647-e01558f9b34e"}]},{"content":"Rotated #luna gains into #fxs and got an almost 50% return in less than 24hrs 😵 even if frax goes up a little higher I think it comes back down to earth for a bit, taking about 40% off and see what happens, but pretty happy with those results","seen_by":[{"annotator":"laurens.de.bruin99@gmail.com","annotator_id":1}],"metadata":{"":23,"id":"1510299696664768515","label":"?"},"example_id":"28b95121-a04e-4575-bf48-988ee925124a","annotations":[],"classifications":[{"correct":null,"class_id":"2fa03333-2670-491d-942e-6fe416b1e212","reviewed":false,"classname":"Unrelated","example_id":"28b95121-a04e-4575-bf48-988ee925124a","classified_by":[{"annotator":"laurens.de.bruin99@gmail.com","timestamp":"2022-04-16T13:17:25.329+00:00","annotator_id":1}],"definition_id":"0bb07793-f67f-4184-8647-e01558f9b34e"}]},{"content":"40k level lost. \n\n$37k #BTC next\n\n#Cryptocrash wasn't supposed to be until May guys. Stop killing my vibe. Sheesh.\n\n🩳 season open for biz 👌🔥🔥","seen_by":[{"annotator":"laurens.de.bruin99@gmail.com","annotator_id":1}],"metadata":{"":24,"id":"1513615292391477248","label":"?"},"example_id":"331629ad-3826-4787-bd42-e184db0ad750","annotations":[],"classifications":[{"correct":null,"class_id":"6d58be54-780e-41ca-95e9-aedfc3f93432","reviewed":false,"classname":"Negative","example_id":"331629ad-3826-4787-bd42-e184db0ad750","classified_by":[{"annotator":"laurens.de.bruin99@gmail.com","timestamp":"2022-04-16T13:12:06.853+00:00","annotator_id":1}],"definition_id":"0bb07793-f67f-4184-8647-e01558f9b34e"}]},{"content":"Is it me or does satoshi island look like one giant rug pull waiting to happen lol \n\n#bitcoin #cryptocurrency #satoshiisland","seen_by":[{"annotator":"laurens.de.bruin99@gmail.com","annotator_id":1}],"metadata":{"":25,"id":"1510653014465515520","label":"?"},"example_id":"e01b8dac-c206-464b-aa32-4d8179024d03","annotations":[],"classifications":[{"correct":null,"class_id":"2fa03333-2670-491d-942e-6fe416b1e212","reviewed":false,"classname":"Unrelated","example_id":"e01b8dac-c206-464b-aa32-4d8179024d03","classified_by":[{"annotator":"laurens.de.bruin99@gmail.com","timestamp":"2022-04-16T13:11:37.936+00:00","annotator_id":1}],"definition_id":"0bb07793-f67f-4184-8647-e01558f9b34e"}]},{"content":"it's pumppinggggg. #eth #NFTs","seen_by":[{"annotator":"laurens.de.bruin99@gmail.com","annotator_id":1}],"metadata":{"":26,"id":"1510639557603176457","label":"?"},"example_id":"de9e1183-60e4-4b8b-be8e-37ec484e9add","annotations":[],"classifications":[{"correct":null,"class_id":"7f749090-d1fe-4bbb-9fd7-75aae0b529cc","reviewed":false,"classname":"Positive","example_id":"de9e1183-60e4-4b8b-be8e-37ec484e9add","classified_by":[{"annotator":"laurens.de.bruin99@gmail.com","timestamp":"2022-04-16T13:11:05.642+00:00","annotator_id":1}],"definition_id":"0bb07793-f67f-4184-8647-e01558f9b34e"}]},{"content":"#SlothTrading🦥 made a new prediction for #ETH on 04/05 at 09:59 UTC (1 hour timeframe)\n\n💵Current value: $3,524.77\n\n🎯Target value: $3,520.02 (📉-0.13%)\n\n🤖Confidence: 59%\n\n💰Last 7 days profits for this asset in this timeframe: 8.18%\n\n⏰Hourly updates on our website","seen_by":[{"annotator":"laurens.de.bruin99@gmail.com","annotator_id":1}],"metadata":{"":27,"id":"1511267930398461953","label":"?"},"example_id":"16c37ae6-4809-4a26-860e-ab3f98b2462c","annotations":[],"classifications":[{"correct":null,"class_id":"2fa03333-2670-491d-942e-6fe416b1e212","reviewed":false,"classname":"Unrelated","example_id":"16c37ae6-4809-4a26-860e-ab3f98b2462c","classified_by":[{"annotator":"laurens.de.bruin99@gmail.com","timestamp":"2022-04-16T13:18:08.534+00:00","annotator_id":1}],"definition_id":"0bb07793-f67f-4184-8647-e01558f9b34e"}]},{"content":"If you invested in $FTT a year ago\nHere's how you're doing today:\n $100 --&gt; $124\n $500 --&gt; $624\n $1000 --&gt; $1249\n $10,000 --&gt; $12498\n #FTX-TOKEN #crypto","seen_by":[{"annotator":"laurens.de.bruin99@gmail.com","annotator_id":1}],"metadata":{"":28,"id":"1510258388810272768","label":"?"},"example_id":"454be68a-a0e6-4a86-bacc-e69420800a94","annotations":[],"classifications":[{"correct":null,"class_id":"2fa03333-2670-491d-942e-6fe416b1e212","reviewed":false,"classname":"Unrelated","example_id":"454be68a-a0e6-4a86-bacc-e69420800a94","classified_by":[{"annotator":"laurens.de.bruin99@gmail.com","timestamp":"2022-04-16T13:11:29.697+00:00","annotator_id":1}],"definition_id":"0bb07793-f67f-4184-8647-e01558f9b34e"}]},{"content":"Rumors of Apple utilizing Bitcoin in some capacity\n#Bitcoin","seen_by":[{"annotator":"laurens.de.bruin99@gmail.com","annotator_id":1}],"metadata":{"":29,"id":"1511087715760369664","label":"?"},"example_id":"f6642351-4cc3-4835-8f22-33009233de81","annotations":[],"classifications":[{"correct":null,"class_id":"2fa03333-2670-491d-942e-6fe416b1e212","reviewed":false,"classname":"Unrelated","example_id":"f6642351-4cc3-4835-8f22-33009233de81","classified_by":[{"annotator":"laurens.de.bruin99@gmail.com","timestamp":"2022-04-16T13:14:03.813+00:00","annotator_id":1}],"definition_id":"0bb07793-f67f-4184-8647-e01558f9b34e"}]},{"content":"Gas used in currently pending transactions:\n\n🚀 15 seconds &gt;&gt;&gt;&gt; 73 Gwei\n🚗 1 minute  &gt;&gt;&gt;&gt;&gt; 58 Gwei\n🐌 3 minutes &gt;&gt;&gt;&gt;&gt; 49 Gwei\n🦥 &gt;10 minutes &gt;&gt;&gt; 45 Gwei\n\n#Ethereum #ETH #GasPrice","seen_by":[{"annotator":"laurens.de.bruin99@gmail.com","annotator_id":1}],"metadata":{"":30,"id":"1511241966507417602","label":"?"},"example_id":"b2706241-3584-4136-80e9-b363c463ff52","annotations":[],"classifications":[{"correct":null,"class_id":"57fba206-3865-4375-8c99-40602e7aa718","reviewed":false,"classname":"Neutral","example_id":"b2706241-3584-4136-80e9-b363c463ff52","classified_by":[{"annotator":"laurens.de.bruin99@gmail.com","timestamp":"2022-04-16T13:16:18.049+00:00","annotator_id":1}],"definition_id":"0bb07793-f67f-4184-8647-e01558f9b34e"}]},{"content":"Missing #Bitcoin Miami 😔😔","seen_by":[{"annotator":"laurens.de.bruin99@gmail.com","annotator_id":1}],"metadata":{"":31,"id":"1511088333535219712","label":"?"},"example_id":"f0101be5-81c9-4f76-953f-fe5494260c37","annotations":[],"classifications":[{"correct":null,"class_id":"2fa03333-2670-491d-942e-6fe416b1e212","reviewed":false,"classname":"Unrelated","example_id":"f0101be5-81c9-4f76-953f-fe5494260c37","classified_by":[{"annotator":"laurens.de.bruin99@gmail.com","timestamp":"2022-04-16T13:17:00.995+00:00","annotator_id":1}],"definition_id":"0bb07793-f67f-4184-8647-e01558f9b34e"}]},{"content":"#Bitcoin price in Canadian Dollar $BTC $XBT $BTCCAD \nBTC Price Now : 51,465.25$ CAD \nAvg Last Hour : 51,647.69$ \nAvg 24 Hours : 53,194.04$ \n24h Change : -4.27% \n24h Low : 51,440.94$ \n24h High : 54,598.04$  \nMore information here https://t.co/AnKnaDahL6 https://t.co/fRegMCdBdF","seen_by":[{"annotator":"laurens.de.bruin99@gmail.com","annotator_id":1}],"metadata":{"":32,"id":"1513532343432232974","label":"?"},"example_id":"39c66286-541b-42ed-ae7b-cc60fc6aad95","annotations":[],"classifications":[{"correct":null,"class_id":"6d58be54-780e-41ca-95e9-aedfc3f93432","reviewed":false,"classname":"Negative","example_id":"39c66286-541b-42ed-ae7b-cc60fc6aad95","classified_by":[{"annotator":"laurens.de.bruin99@gmail.com","timestamp":"2022-04-16T13:11:47.954+00:00","annotator_id":1}],"definition_id":"0bb07793-f67f-4184-8647-e01558f9b34e"}]},{"content":"Meanwhile, here's some BTC update, from my point of view.\n\nWe've just lost a really important support at 44.2k, creating a possible lower low on the daily timeframe. We could possibly see a little bit more of a dump in the next hours. The 4h RSI hit the oversold point tho. #BTC","seen_by":[{"annotator":"laurens.de.bruin99@gmail.com","annotator_id":1}],"metadata":{"":33,"id":"1511784198549475334","label":"?"},"example_id":"7e40d153-7ef8-4c53-861e-0e34dd068e0a","annotations":[],"classifications":[{"correct":null,"class_id":"6d58be54-780e-41ca-95e9-aedfc3f93432","reviewed":false,"classname":"Negative","example_id":"7e40d153-7ef8-4c53-861e-0e34dd068e0a","classified_by":[{"annotator":"laurens.de.bruin99@gmail.com","timestamp":"2022-04-16T13:12:55.8+00:00","annotator_id":1}],"definition_id":"0bb07793-f67f-4184-8647-e01558f9b34e"}]},{"content":"🐝 🐝 Hive minds think alike where the @swarms_ai #AVAX community at? 🐝 🐝 \n\nWhat’s a Campfire without our frenly swarm folks.\n\n#AVAX #avalanche #AvaxNftRush #knowledgeavalanche","seen_by":[{"annotator":"laurens.de.bruin99@gmail.com","annotator_id":1}],"metadata":{"":34,"id":"1510653669934465026","label":"?"},"example_id":"5ec40bd5-2fa3-4039-ac40-b436ed2f7a61","annotations":[],"classifications":[{"correct":null,"class_id":"2fa03333-2670-491d-942e-6fe416b1e212","reviewed":false,"classname":"Unrelated","example_id":"5ec40bd5-2fa3-4039-ac40-b436ed2f7a61","classified_by":[{"annotator":"laurens.de.bruin99@gmail.com","timestamp":"2022-04-16T13:11:56.643+00:00","annotator_id":1}],"definition_id":"0bb07793-f67f-4184-8647-e01558f9b34e"}]},{"content":"#bitcoin already prices in stock market on Sunday night early Monday morning. Why I knew stocks would@open down today and why I knew Bitcoin wouldn't fall off a cliff when stocks opened. $btc leads the way on weekends and at nicut/early morning.","seen_by":[{"annotator":"laurens.de.bruin99@gmail.com","annotator_id":1}],"metadata":{"":35,"id":"1513523130953834508","label":"?"},"example_id":"1b647dd0-3314-4647-9281-a1044801b493","annotations":[],"classifications":[{"correct":null,"class_id":"2fa03333-2670-491d-942e-6fe416b1e212","reviewed":false,"classname":"Unrelated","example_id":"1b647dd0-3314-4647-9281-a1044801b493","classified_by":[{"annotator":"laurens.de.bruin99@gmail.com","timestamp":"2022-04-16T13:15:52.389+00:00","annotator_id":1}],"definition_id":"0bb07793-f67f-4184-8647-e01558f9b34e"}]},{"content":"$1.6B in gold vs $1.6B in Bitcoin.\n\nWhich one of these can be mined, stored, and transported with 100% renewable green energy? #Bitcoin https://t.co/y1WmXNFVs3","seen_by":[{"annotator":"laurens.de.bruin99@gmail.com","annotator_id":1}],"metadata":{"":36,"id":"1512103745139654661","label":"?"},"example_id":"49cd7c5f-2420-4205-97c2-30da7260d548","annotations":[],"classifications":[{"correct":null,"class_id":"2fa03333-2670-491d-942e-6fe416b1e212","reviewed":false,"classname":"Unrelated","example_id":"49cd7c5f-2420-4205-97c2-30da7260d548","classified_by":[{"annotator":"laurens.de.bruin99@gmail.com","timestamp":"2022-04-16T13:13:14.278+00:00","annotator_id":1}],"definition_id":"0bb07793-f67f-4184-8647-e01558f9b34e"}]},{"content":"#BTC made its stop on the Daily Fibo retracement. https://t.co/dosR8vqkpL","seen_by":[{"annotator":"laurens.de.bruin99@gmail.com","annotator_id":1}],"metadata":{"":37,"id":"1512110468617359367","label":"?"},"example_id":"22725619-2dfc-4a51-b793-5ca582d1e897","annotations":[],"classifications":[{"correct":null,"class_id":"2fa03333-2670-491d-942e-6fe416b1e212","reviewed":false,"classname":"Unrelated","example_id":"22725619-2dfc-4a51-b793-5ca582d1e897","classified_by":[{"annotator":"laurens.de.bruin99@gmail.com","timestamp":"2022-04-16T13:16:00.328+00:00","annotator_id":1}],"definition_id":"0bb07793-f67f-4184-8647-e01558f9b34e"}]},{"content":"#Bitcoin Mining is going to save the world.\n- Shark Tank’s Kevin O’Leary https://t.co/31PmAIgXOO","seen_by":[{"annotator":"laurens.de.bruin99@gmail.com","annotator_id":1}],"metadata":{"":38,"id":"1512109310981165059","label":"?"},"example_id":"d9b5e0a6-5f57-4ade-8d23-76c92f643860","annotations":[],"classifications":[{"correct":null,"class_id":"2fa03333-2670-491d-942e-6fe416b1e212","reviewed":false,"classname":"Unrelated","example_id":"d9b5e0a6-5f57-4ade-8d23-76c92f643860","classified_by":[{"annotator":"laurens.de.bruin99@gmail.com","timestamp":"2022-04-16T13:11:51.444+00:00","annotator_id":1}],"definition_id":"0bb07793-f67f-4184-8647-e01558f9b34e"}]},{"content":"📈#BNB | Increasing  1.47%\nAverage price for the last hour: BNBUSDT - 453.0","seen_by":[{"annotator":"laurens.de.bruin99@gmail.com","annotator_id":1}],"metadata":{"":39,"id":"1511238779348131840","label":"?"},"example_id":"f66c8e77-749c-4bd7-9a76-93c93bfb90ca","annotations":[],"classifications":[{"correct":null,"class_id":"7f749090-d1fe-4bbb-9fd7-75aae0b529cc","reviewed":false,"classname":"Positive","example_id":"f66c8e77-749c-4bd7-9a76-93c93bfb90ca","classified_by":[{"annotator":"laurens.de.bruin99@gmail.com","timestamp":"2022-04-16T13:10:51.688+00:00","annotator_id":1}],"definition_id":"0bb07793-f67f-4184-8647-e01558f9b34e"}]},{"content":"@binance #Bitcoin #BitcoinButton #Binance\n\nI love Bitcoin a lot 😍 https://t.co/TBu8PrGoaK","seen_by":[{"annotator":"laurens.de.bruin99@gmail.com","annotator_id":1}],"metadata":{"":40,"id":"1513647936084668416","label":"?"},"example_id":"f8590e41-30d6-4cf9-acfd-7f9de20efeb2","annotations":[],"classifications":[{"correct":null,"class_id":"7f749090-d1fe-4bbb-9fd7-75aae0b529cc","reviewed":false,"classname":"Positive","example_id":"f8590e41-30d6-4cf9-acfd-7f9de20efeb2","classified_by":[{"annotator":"laurens.de.bruin99@gmail.com","timestamp":"2022-04-16T13:13:50.475+00:00","annotator_id":1}],"definition_id":"0bb07793-f67f-4184-8647-e01558f9b34e"}]},{"content":"#XRP is getting ready for the biggest pumping!! #crypto #binance #altcoin\nhttps://t.co/R1AzcQ7A59","seen_by":[{"annotator":"laurens.de.bruin99@gmail.com","annotator_id":1}],"metadata":{"":41,"id":"1513599343688765443","label":"?"},"example_id":"ffcb9145-3c15-4238-963b-526f45c3b662","annotations":[],"classifications":[{"correct":null,"class_id":"7f749090-d1fe-4bbb-9fd7-75aae0b529cc","reviewed":false,"classname":"Positive","example_id":"ffcb9145-3c15-4238-963b-526f45c3b662","classified_by":[{"annotator":"laurens.de.bruin99@gmail.com","timestamp":"2022-04-16T13:11:33.246+00:00","annotator_id":1}],"definition_id":"0bb07793-f67f-4184-8647-e01558f9b34e"}]},{"content":"#Bitcoin ended up going into the golden pocket but went even further down, trendline not holding it either, but we could be in a situation like the two other times it broke the trendline and got back in it, which is why I think price might bottom at 39,154 to get that 3rd peak. https://t.co/RRLPrxNE5C","seen_by":[{"annotator":"laurens.de.bruin99@gmail.com","annotator_id":1}],"metadata":{"":42,"id":"1513591380593065988","label":"?"},"example_id":"8c1a32a9-f5d0-4b00-856c-c8a16e838327","annotations":[],"classifications":[{"correct":null,"class_id":"6d58be54-780e-41ca-95e9-aedfc3f93432","reviewed":false,"classname":"Negative","example_id":"8c1a32a9-f5d0-4b00-856c-c8a16e838327","classified_by":[{"annotator":"laurens.de.bruin99@gmail.com","timestamp":"2022-04-16T13:16:57.521+00:00","annotator_id":1}],"definition_id":"0bb07793-f67f-4184-8647-e01558f9b34e"}]},{"content":"@anndylian We aim to go to Mars, not the moon! @BscPitbull $PIT #PitbullBigListing #Bitcoin #btc","seen_by":[{"annotator":"laurens.de.bruin99@gmail.com","annotator_id":1}],"metadata":{"":44,"id":"1511785734415470594","label":"?"},"example_id":"42d0a8ab-9723-4150-8eb0-f7072ae9df9b","annotations":[],"classifications":[{"correct":null,"class_id":"2fa03333-2670-491d-942e-6fe416b1e212","reviewed":false,"classname":"Unrelated","example_id":"42d0a8ab-9723-4150-8eb0-f7072ae9df9b","classified_by":[{"annotator":"laurens.de.bruin99@gmail.com","timestamp":"2022-04-16T13:10:57.385+00:00","annotator_id":1}],"definition_id":"0bb07793-f67f-4184-8647-e01558f9b34e"}]},{"content":"have a look at the rules and don't miss #xrp #garlinghouse\n\nhttps://t.co/Tiq5M9Kshe","seen_by":[{"annotator":"laurens.de.bruin99@gmail.com","annotator_id":1}],"metadata":{"":45,"id":"1513532207591157763","label":"?"},"example_id":"6ed194fb-2ec6-4d57-bc53-33f0ee430779","annotations":[],"classifications":[{"correct":null,"class_id":"2fa03333-2670-491d-942e-6fe416b1e212","reviewed":false,"classname":"Unrelated","example_id":"6ed194fb-2ec6-4d57-bc53-33f0ee430779","classified_by":[{"annotator":"laurens.de.bruin99@gmail.com","timestamp":"2022-04-16T13:14:44.22+00:00","annotator_id":1}],"definition_id":"0bb07793-f67f-4184-8647-e01558f9b34e"}]},{"content":"Terra - LUNA\nPrice: $114.94\nChange in 1h: -0.38256474%\nMarket cap: $40,531,593,756.71\nRanking: 7\n#Terra #LUNA","seen_by":[{"annotator":"laurens.de.bruin99@gmail.com","annotator_id":1}],"metadata":{"":46,"id":"1511086341236224001","label":"?"},"example_id":"c2be8129-fbf3-4258-80de-ba7a34965a4d","annotations":[],"classifications":[{"correct":null,"class_id":"6d58be54-780e-41ca-95e9-aedfc3f93432","reviewed":false,"classname":"Negative","example_id":"c2be8129-fbf3-4258-80de-ba7a34965a4d","classified_by":[{"annotator":"laurens.de.bruin99@gmail.com","timestamp":"2022-04-16T13:14:00.078+00:00","annotator_id":1}],"definition_id":"0bb07793-f67f-4184-8647-e01558f9b34e"}]},{"content":"@cardano_whale @Crypt0Jed1 Probably also a 'closer what I 'm used to' for many devs. But that also raises the usecas question.","seen_by":[{"annotator":"laurens.de.bruin99@gmail.com","annotator_id":1}],"metadata":{"":47,"id":"1510630770829897729","label":"?"},"example_id":"d5ecd616-fb94-4364-98ec-18dd96e99ba3","annotations":[],"classifications":[{"correct":null,"class_id":"2fa03333-2670-491d-942e-6fe416b1e212","reviewed":false,"classname":"Unrelated","example_id":"d5ecd616-fb94-4364-98ec-18dd96e99ba3","classified_by":[{"annotator":"laurens.de.bruin99@gmail.com","timestamp":"2022-04-16T13:12:22.332+00:00","annotator_id":1}],"definition_id":"0bb07793-f67f-4184-8647-e01558f9b34e"}]},{"content":"🎟Get Lucky Tickets at @LuckyHash_ for chances to 100x your idle cryptos! Now support #Dogecoin #WINklink #TRX #XRP. Join now to gain extra rewards for buying Lucky Tickets👉 https://t.co/yKkMox0CIl","seen_by":[{"annotator":"laurens.de.bruin99@gmail.com","annotator_id":1}],"metadata":{"":48,"id":"1513540194196422658","label":"?"},"example_id":"25752afa-521e-497b-8042-0e45ee36d862","annotations":[],"classifications":[{"correct":null,"class_id":"2fa03333-2670-491d-942e-6fe416b1e212","reviewed":false,"classname":"Unrelated","example_id":"25752afa-521e-497b-8042-0e45ee36d862","classified_by":[{"annotator":"laurens.de.bruin99@gmail.com","timestamp":"2022-04-16T13:12:32.512+00:00","annotator_id":1}],"definition_id":"0bb07793-f67f-4184-8647-e01558f9b34e"}]},{"content":"The long term strength of any #crypto is how its core community handles the inevitable and prolonged dips.  These are the people who carry it through the bear market, when everyone else is running after the new shiny objects that are outperforming atm.","seen_by":[{"annotator":"laurens.de.bruin99@gmail.com","annotator_id":1}],"metadata":{"":49,"id":"1510640362750103565","label":"?"},"example_id":"2230a09c-8e78-4238-b903-d2a625701d08","annotations":[],"classifications":[{"correct":null,"class_id":"2fa03333-2670-491d-942e-6fe416b1e212","reviewed":false,"classname":"Unrelated","example_id":"2230a09c-8e78-4238-b903-d2a625701d08","classified_by":[{"annotator":"laurens.de.bruin99@gmail.com","timestamp":"2022-04-16T13:17:11.234+00:00","annotator_id":1}],"definition_id":"0bb07793-f67f-4184-8647-e01558f9b34e"}]}],"schema":{"id":"66052613-be96-45d7-8597-ee4501d1373f","archived":false,"slug":"sa-final","name":"SA Final","tags":[],"project":"a2d8d9b1-3bd0-40b0-9000-88955966d058","classification_types":[{"id":"6d58be54-780e-41ca-95e9-aedfc3f93432","name":"Negative","schema_id":"66052613-be96-45d7-8597-ee4501d1373f"},{"id":"57fba206-3865-4375-8c99-40602e7aa718","name":"Neutral","schema_id":"66052613-be96-45d7-8597-ee4501d1373f"},{"id":"7f749090-d1fe-4bbb-9fd7-75aae0b529cc","name":"Positive","schema_id":"66052613-be96-45d7-8597-ee4501d1373f"},{"id":"2fa03333-2670-491d-942e-6fe416b1e212","name":"Unrelated","schema_id":"66052613-be96-45d7-8597-ee4501d1373f"}],"project_id":"a2d8d9b1-3bd0-40b0-9000-88955966d058","models":[{"id":"382dc250-e83e-448b-a6e7-1591f278d88f","url":"/api/v1/projects/default/schemas/sa-final/models/sa-final-ad-hoc-dict/","slug":"sa-final-ad-hoc-dict","name":"SA Final ad hoc dict","metadata":{},"schema_id":"66052613-be96-45d7-8597-ee4501d1373f"}],"editable":false,"is_multiclass":false},"dataset":{"id":"0693bacd-6127-40e8-8464-859d40600b23","slug":"16-04-15-10","url":"/api/v1/projects/default/datasets/16-04-15-10/","name":"16-04-15-10","id_field":null,"content_field":"text","aggregation_field":null,"order_field":null,"project_id":"a2d8d9b1-3bd0-40b0-9000-88955966d058","upload_status":"started","archived":false,"editable":false},"relations":[],"name":"16-04-15-10","annotators_per_example":"1"}